p2py
