Metadata-Version: 2.1
Name: p2py
Version: 0.23
Summary: The simplest peer to peer networking Python library
Home-page: https://github.com/ipds/p2py
Author: Adam Szokalski
Author-email: aszokalski@ipds.team
License: AGPLv3
Download-URL: https://github.com/ipds/p2py/archive/0.1.tar.gz
Keywords: p2p,peer to peer,ipds
Platform: all
Classifier: Development Status :: 3 - Alpha
Classifier: Topic :: Software Development :: Build Tools
Classifier: License :: OSI Approved :: GNU Affero General Public License v3
Classifier: Programming Language :: Python :: 3.6
Classifier: Programming Language :: Python :: 3.7
Classifier: Programming Language :: Python :: 3.8
Classifier: Topic :: System :: Networking
